casatasks/LICENSE.txt
casatasks/__init__.py
casatasks/__main__.py
casatasks/accor.py
casatasks/apparentsens.py
casatasks/appendantab.py
casatasks/applycal.py
casatasks/asdmsummary.py
casatasks/bandpass.py
casatasks/blcal.py
casatasks/calstat.py
casatasks/clearcal.py
casatasks/clearstat.py
casatasks/concat.py
casatasks/conjugatevis.py
casatasks/cvel.py
casatasks/cvel2.py
casatasks/deconvolve.py
casatasks/defintent.py
casatasks/delmod.py
casatasks/exportasdm.py
casatasks/exportfits.py
casatasks/exportuvfits.py
casatasks/feather.py
casatasks/fixplanets.py
casatasks/fixvis.py
casatasks/flagcmd.py
casatasks/flagdata.py
casatasks/flagmanager.py
casatasks/fluxscale.py
casatasks/fringefit.py
casatasks/ft.py
casatasks/gaincal.py
casatasks/gencal.py
casatasks/getantposalma.py
casatasks/getcalmodvla.py
casatasks/getephemtable.py
casatasks/hanningsmooth.py
casatasks/imbaseline.py
casatasks/imcollapse.py
casatasks/imcontsub.py
casatasks/imdev.py
casatasks/imfit.py
casatasks/imhead.py
casatasks/imhistory.py
casatasks/immath.py
casatasks/immoments.py
casatasks/impbcor.py
casatasks/importasap.py
casatasks/importasdm.py
casatasks/importatca.py
casatasks/importfits.py
casatasks/importfitsidi.py
casatasks/importgmrt.py
casatasks/importmiriad.py
casatasks/importnro.py
casatasks/importuvfits.py
casatasks/importvla.py
casatasks/impv.py
casatasks/imrebin.py
casatasks/imreframe.py
casatasks/imregrid.py
casatasks/imsmooth.py
casatasks/imstat.py
casatasks/imsubimage.py
casatasks/imtrans.py
casatasks/imval.py
casatasks/initweights.py
casatasks/listcal.py
casatasks/listfits.py
casatasks/listhistory.py
casatasks/listobs.py
casatasks/listpartition.py
casatasks/listsdm.py
casatasks/listvis.py
casatasks/makemask.py
casatasks/mstransform.py
casatasks/msuvbin.py
casatasks/msuvbinflag.py
casatasks/nrobeamaverage.py
casatasks/partition.py
casatasks/phaseshift.py
casatasks/plotants.py
casatasks/plotbandpass.py
casatasks/plotprofilemap.py
casatasks/plotweather.py
casatasks/polcal.py
casatasks-6.7.2.42.dist-info/METADATA
casatasks-6.7.2.42.dist-info/WHEEL
casatasks-6.7.2.42.dist-info/top_level.txt
casatasks-6.7.2.42.dist-info/RECORD
